dtshare/__init__.py
dtshare/air/__init__.py
dtshare/air/air_hebei.py
dtshare/air/aqi_study.py
dtshare/air/aqi_utils.py
dtshare/air/cons.py
dtshare/air/time_and_date.py
dtshare/article/__init__.py
dtshare/article/cons.py
dtshare/article/epu_index.py
dtshare/article/ff_factor.py
dtshare/article/risk_rv.py
dtshare/bank/__init__.py
dtshare/bank/bank_cbirc.py
dtshare/bank/bank_cbirc_20191114.py
dtshare/bank/bank_cbirc_20191115.py
dtshare/bank/bank_cbirc_2020.py
dtshare/bank/cons.py
dtshare/bond/__init__.py
dtshare/bond/bond_bank.py
dtshare/bond/china_bond.py
dtshare/bond/china_repo.py
dtshare/bond/cons.py
dtshare/bond/investing_bond.py
dtshare/bond/zh_bond_cov_sina.py
dtshare/bond/zh_bond_sina.py
dtshare/charity/__init__.py
dtshare/charity/charity_china.py
dtshare/cost/__init__.py
dtshare/cost/cons.py
dtshare/cost/cost_living.py
dtshare/currency/__init__.py
dtshare/currency/currency.py
dtshare/economic/__init__.py
dtshare/economic/class_macro_usa.py
dtshare/economic/cons.py
dtshare/economic/macro_bank.py
dtshare/economic/macro_china.py
dtshare/economic/macro_constitute.py
dtshare/economic/macro_euro.py
dtshare/economic/macro_other.py
dtshare/economic/macro_usa.py
dtshare/economic/marco_cnbs.py
dtshare/energy/__init__.py
dtshare/energy/energy_carbon.py
dtshare/event/__init__.py
dtshare/event/cons.py
dtshare/event/franchise.py
dtshare/event/sos.py
dtshare/file_fold/__init__.py
dtshare/file_fold/calendar.json
dtshare/fortune/__init__.py
dtshare/fortune/cons.py
dtshare/fortune/fortune_500.py
dtshare/fortune/it_juzi.py
dtshare/fund/__init__.py
dtshare/fund/cons.py
dtshare/fund/fund_amac.py
dtshare/fund/fund_em.py
dtshare/fund/fund_interface.py
dtshare/fund/fund_simu.py
dtshare/fund/fund_zdzk.py
dtshare/futures/__init__.py
dtshare/futures/basis.py
dtshare/futures/cons.py
dtshare/futures/cot.py
dtshare/futures/daily_bar.py
dtshare/futures/futures_inventory.py
dtshare/futures/futures_rule.py
dtshare/futures/hf_futures_sina.py
dtshare/futures/international_futures.py
dtshare-1.0.3.dist-info/LICENSE
dtshare-1.0.3.dist-info/METADATA
dtshare-1.0.3.dist-info/WHEEL
dtshare-1.0.3.dist-info/top_level.txt
dtshare-1.0.3.dist-info/RECORD
