Metadata-Version: 2.1
Name: dtshare
Version: 1.0.3
Summary: Open financial data
Home-page: https://github.com/DTShare/dtshare
Author: Tony Du
License: MIT
Keywords: bigdata,stock,option,futures,fund,bond,finance index,finance,quant,quantitative,trading,algotrading
Platform: UNKNOWN
Classifier: Programming Language :: Python :: 3.6
Classifier: Programming Language :: Python :: 3.7
Classifier: Programming Language :: Python :: 3.8
Classifier: License :: OSI Approved :: MIT License
Classifier: Operating System :: OS Independent
Requires-Python: >=3.5
Requires-Dist: numpy (>=1.15.4)
Requires-Dist: pandas (>=0.24)
Requires-Dist: requests (>=2.22.0)
Requires-Dist: demjson (>=2.2.4)
Requires-Dist: pyexecjs (>=1.5.1)
Requires-Dist: pillow (>=6.2.0)
Requires-Dist: pypinyin (>=0.35.0)
Requires-Dist: pycryptodomex (>=3.9.4)
Requires-Dist: html5lib (>=1.0.1)
Requires-Dist: requests-html (>=0.10.0)
Requires-Dist: scikit-learn (>=0.22)
Requires-Dist: fonttools (>=4.2.2)
Requires-Dist: xlrd (>=1.2.0)
Requires-Dist: bs4 (>=0.0.1)
Requires-Dist: lxml (>=4.2.1)
